{"backupType":"DELETE_SALE","brandId":2,"customerId":10592,"idempotencyKey":"7d173529-5cc2-46a1-adb5-87b9820d2e3a","initializedAt":"2025-07-03T19:01:20.753Z","id":-5,"orders":[{"divisionKey":-1,"initializedAt":"2025-07-03T19:01:20.777Z","paymentConditionId":13054,"priceListId":44877,"deliveryDate":"","deliveryPeriod":"","id":-1,"identifier":"","discounts":[],"orderFields":[],"skus":[{"id":4452531,"distributionCenterId":1,"unitPrice":79.9,"evaluatedUnitPrice":79.9,"integrationId":"5.15965.0177.G.0","quantity":0},{"id":4452532,"distributionCenterId":1,"unitPrice":79.9,"evaluatedUnitPrice":79.9,"integrationId":"5.15965.0177.M.0","quantity":2},{"id":4452533,"distributionCenterId":1,"unitPrice":79.9,"evaluatedUnitPrice":79.9,"integrationId":"5.15965.0177.P.0","quantity":2},{"id":4452534,"distributionCenterId":1,"unitPrice":79.9,"evaluatedUnitPrice":79.9,"integrationId":"5.15965.0177.PP.0","quantity":2},{"id":8353618,"distributionCenterId":1,"unitPrice":79.9,"evaluatedUnitPrice":79.9,"integrationId":"5.15965.0177.GG.0","quantity":0},{"id":4455014,"distributionCenterId":1,"unitPrice":194.9,"evaluatedUnitPrice":194.9,"integrationId":"5.18102.0282.U.0","quantity":2},{"id":4455015,"distributionCenterId":1,"unitPrice":194.9,"evaluatedUnitPrice":194.9,"integrationId":"5.18102.0492.U.0","quantity":2}]}]}